{
    "code": 1,
    "message": "操作成功",
    "messageDetail": "",
    "publicInfo": "未知",
    "onlineInfo": null,
    "battleInfo": null,
    "isHaveCurry": 0,
    "curryMap": null,
    "data": {
        "gameType": "CUSTOM_GAME",
        "gameMode": "CLASSIC",
        "wgBattleDetailInfo": [
            {
                "scoreInfo": "5/7/2",
                "skinIndexName": "驯龙炮手 崔丝塔娜<br>（传说）",
                "echartsMap": {
                    "totalDamageDealtPrv": 14439,
                    "totalDamageTakenPrv": 25714,
                    "killAssisScorePrv": 47,
                    "goldEarned": 11120,
                    "totalDamageTakenInfo": "承伤\n16103\n(25714)",
                    "goldEarnedMax": 12786,
                    "killAssisMax": 100,
                    "scorePrv": 3.9,
                    "score": 4.5,
                    "killAssisScore": 50,
                    "totalDamageDealtMax": 16105,
                    "totalDamageTakenMax": 28380,
                    "totalDamageDealtInfo": "伤害\n12216\n(14439)",
                    "killAssisInfo": "参团\n50%\n(47%)",
                    "gameScoreMax": 4.5,
                    "totalDamageDealt": 12216,
                    "totalDamageTaken": 16103,
                    "goldEarnedPrv": 9249,
                    "goldEarnedInfo": "金币\n11120\n(9249)",
                    "gameScoreInfo": "评分\n4.5\n(3.9)"
                },
                "goldEarned": 11.2,
                "playerSubteamPlacement": "0",
                "skinUrlInfo": "https://wegame.gtimg.com/g.26-r.c2d3c/helper/lol/assis/images/resources/skins/original/18-010.jpg",
                "scoreInfoNum": 4.5,
                "detailChampionId": "18",
                "nickNameStr": "Mujin#73735",
                "wasSvp": "0",
                "win": "Fail",
                "zhuangbei2": 6676,
                "dengji": "12",
                "zhuangbei1": 3031,
                "zhuangbei4": 0,
                "zhuangbei3": 6675,
                "biaoxianInfo": [],
                "zhuangbei6": 0,
                "zhuangbei5": 0,
                "wasMvp": "0",
                "zhuangbei7": 3363,
                "nickName": "Mujin#73735",
                "detailSperk4": 8014,
                "detailSperk5": 8135,
                "detailSperk6": 8126,
                "playerSubteam": "0",
                "detailSperk1": 8008,
                "tierInfoId": 0,
                "detailSperk2": 9111,
                "detailSperk3": 9103,
                "detailRune2": 21,
                "detailRune1": 4,
                "qszhl": "0.704",
                "duanweiInfo": "",
                "totalDamageDealt": 12.3,
                "teamId": "200",
                "translateAreaId": 1,
                "position": "BOTTOM",
                "openIdNow": "aBUpk/8D+kpkaSYhfNgg31v79Zs7CagB3mTW89J2kaQ=",
                "guimo": 5
            },
            {
                "scoreInfo": "3/9/7",
                "skinIndexName": "黑夜使者 亚索<br>（传说）",
                "echartsMap": {
                    "totalDamageDealtPrv": 14439,
                    "totalDamageTakenPrv": 25714,
                    "killAssisScorePrv": 47,
                    "goldEarned": 8732,
                    "totalDamageTakenInfo": "承伤\n25084\n(25714)",
                    "goldEarnedMax": 10915,
                    "killAssisMax": 100,
                    "scorePrv": 3.9,
                    "score": 3.7,
                    "killAssisScore": 71,
                    "totalDamageDealtMax": 21769,
                    "totalDamageTakenMax": 28380,
                    "totalDamageDealtInfo": "伤害\n20103\n(14439)",
                    "killAssisInfo": "参团\n71%\n(47%)",
                    "gameScoreMax": 3.9,
                    "totalDamageDealt": 20103,
                    "totalDamageTaken": 25084,
                    "goldEarnedPrv": 9249,
                    "goldEarnedInfo": "金币\n8732\n(9249)",
                    "gameScoreInfo": "评分\n3.7\n(3.9)"
                },
                "goldEarned": 8.8,
                "playerSubteamPlacement": "0",
                "skinUrlInfo": "https://wegame.gtimg.com/g.26-r.c2d3c/helper/lol/assis/images/resources/skins/original/157-009.jpg",
                "scoreInfoNum": 3.7,
                "detailChampionId": "157",
                "nickNameStr": "什么老谭酸菜鱼#83037",
                "wasSvp": "0",
                "win": "Fail",
                "zhuangbei2": 3153,
                "dengji": "13",
                "zhuangbei1": 6672,
                "zhuangbei4": 0,
                "zhuangbei3": 1042,
                "biaoxianInfo": [],
                "zhuangbei6": 3172,
                "zhuangbei5": 0,
                "wasMvp": "0",
                "zhuangbei7": 3363,
                "nickName": "什么老谭酸菜鱼#83037",
                "detailSperk4": 8299,
                "detailSperk5": 8444,
                "detailSperk6": 8451,
                "playerSubteam": "0",
                "detailSperk1": 8008,
                "tierInfoId": 0,
                "detailSperk2": 9101,
                "detailSperk3": 9104,
                "detailRune2": 4,
                "detailRune1": 14,
                "qszhl": "1.475",
                "duanweiInfo": "",
                "totalDamageDealt": 20.2,
                "teamId": "200",
                "translateAreaId": 1,
                "position": "MIDDLE",
                "openIdNow": "oO4vJgPegiYSJ2hYNPjeMqHgXxtd1oco3mTW89J2kaQ=",
                "guimo": 5
            },
            {
                "scoreInfo": "2/1/11",
                "skinIndexName": "嘟！嘟 ！奥恩",
                "echartsMap": {
                    "totalDamageDealtPrv": 21365,
                    "totalDamageTakenPrv": 19078,
                    "killAssisScorePrv": 47,
                    "goldEarned": 9983,
                    "totalDamageTakenInfo": "承伤\n17734\n(19078)",
                    "goldEarnedMax": 13501,
                    "killAssisMax": 100,
                    "scorePrv": 8.3,
                    "score": 8.5,
                    "killAssisScore": 33,
                    "totalDamageDealtMax": 23031,
                    "totalDamageTakenMax": 21744,
                    "totalDamageDealtInfo": "伤害\n15445\n(21365)",
                    "killAssisInfo": "参团\n33%\n(47%)",
                    "gameScoreMax": 8.5,
                    "totalDamageDealt": 15445,
                    "totalDamageTaken": 17734,
                    "goldEarnedPrv": 11835,
                    "goldEarnedInfo": "金币\n9983\n(11835)",
                    "gameScoreInfo": "评分\n8.5\n(8.3)"
                },
                "goldEarned": 10.0,
                "playerSubteamPlacement": "0",
                "skinUrlInfo": "https://wegame.gtimg.com/g.26-r.c2d3c/helper/lol/assis/images/resources/skins/original/516-020.jpg",
                "scoreInfoNum": 8.5,
                "detailChampionId": "516",
                "nickNameStr": "不许责备羊羊#16510",
                "wasSvp": "0",
                "win": "Win",
                "zhuangbei2": 1031,
                "dengji": "16",
                "zhuangbei1": 0,
                "zhuangbei4": 3075,
                "zhuangbei3": 3070,
                "biaoxianInfo": [],
                "zhuangbei6": 2502,
                "zhuangbei5": 3047,
                "wasMvp": "0",
                "zhuangbei7": 3340,
                "nickName": "不许责备羊羊#16510",
                "detailSperk4": 8451,
                "detailSperk5": 9105,
                "detailSperk6": 9111,
                "playerSubteam": "0",
                "detailSperk1": 8437,
                "tierInfoId": 0,
                "detailSperk2": 8446,
                "detailSperk3": 8429,
                "detailRune2": 12,
                "detailRune1": 4,
                "qszhl": "0.857",
                "duanweiInfo": "",
                "totalDamageDealt": 15.5,
                "teamId": "100",
                "translateAreaId": 1,
                "position": "TOP",
                "openIdNow": "rs618a0iS9zJW3w/U2uZi0io+5GI64TD3mTW89J2kaQ=",
                "guimo": 5
            },
            {
                "scoreInfo": "21/2/4",
                "skinIndexName": "K/DA 卡莎",
                "echartsMap": {
                    "totalDamageDealtPrv": 21365,
                    "totalDamageTakenPrv": 19078,
                    "killAssisScorePrv": 47,
                    "goldEarned": 17888,
                    "totalDamageTakenInfo": "承伤\n18526\n(19078)",
                    "goldEarnedMax": 19554,
                    "killAssisMax": 100,
                    "scorePrv": 8.3,
                    "score": 14.7,
                    "killAssisScore": 64,
                    "totalDamageDealtMax": 47051,
                    "totalDamageTakenMax": 21744,
                    "totalDamageDealtInfo": "伤害\n45385\n(21365)",
                    "killAssisInfo": "参团\n64%\n(47%)",
                    "gameScoreMax": 14.7,
                    "totalDamageDealt": 45385,
                    "totalDamageTaken": 18526,
                    "goldEarnedPrv": 11835,
                    "goldEarnedInfo": "金币\n17888\n(11835)",
                    "gameScoreInfo": "评分\n14.7\n(8.3)"
                },
                "goldEarned": 17.9,
                "playerSubteamPlacement": "0",
                "skinUrlInfo": "https://wegame.gtimg.com/g.26-r.c2d3c/helper/lol/assis/images/resources/skins/original/145-014.jpg",
                "scoreInfoNum": 14.7,
                "detailChampionId": "145",
                "nickNameStr": "抱走贩星崽子#25713",
                "wasSvp": "0",
                "win": "Win",
                "zhuangbei2": 1083,
                "dengji": "15",
                "zhuangbei1": 1055,
                "zhuangbei4": 6672,
                "zhuangbei3": 3031,
                "biaoxianInfo": [
                    "kill3",
                    "kill4",
                    "god",
                    "money",
                    "hurt2",
                    "soldier",
                    "kill"
                ],
                "zhuangbei6": 3046,
                "zhuangbei5": 3124,
                "wasMvp": "1",
                "zhuangbei7": 3363,
                "nickName": "抱走贩星崽子#25713",
                "detailSperk4": 8014,
                "detailSperk5": 8304,
                "detailSperk6": 8345,
                "playerSubteam": "0",
                "detailSperk1": 8008,
                "tierInfoId": 0,
                "detailSperk2": 9111,
                "detailSperk3": 9103,
                "detailRune2": 4,
                "detailRune1": 21,
                "qszhl": "1.406",
                "duanweiInfo": "",
                "totalDamageDealt": 45.4,
                "teamId": "100",
                "translateAreaId": 1,
                "position": "BOTTOM",
                "openIdNow": "nSVV4wqjL2kkT64X9m9jlDZVpuCWT+Sj3mTW89J2kaQ=",
                "guimo": 5
            },
            {
                "scoreInfo": "1/8/3",
                "skinIndexName": "原皮",
                "echartsMap": {
                    "totalDamageDealtPrv": 14439,
                    "totalDamageTakenPrv": 25714,
                    "killAssisScorePrv": 47,
                    "goldEarned": 6469,
                    "totalDamageTakenInfo": "承伤\n29082\n(25714)",
                    "goldEarnedMax": 10915,
                    "killAssisMax": 100,
                    "scorePrv": 3.9,
                    "score": 3.0,
                    "killAssisScore": 29,
                    "totalDamageDealtMax": 16105,
                    "totalDamageTakenMax": 31748,
                    "totalDamageDealtInfo": "伤害\n12989\n(14439)",
                    "killAssisInfo": "参团\n29%\n(47%)",
                    "gameScoreMax": 3.9,
                    "totalDamageDealt": 12989,
                    "totalDamageTaken": 29082,
                    "goldEarnedPrv": 9249,
                    "goldEarnedInfo": "金币\n6469\n(9249)",
                    "gameScoreInfo": "评分\n3.0\n(3.9)"
                },
                "goldEarned": 6.5,
                "playerSubteamPlacement": "0",
                "skinUrlInfo": "https://wegame.gtimg.com/g.26-r.c2d3c/helper/lol/assis/images/resources/skins/original/50-000.jpg",
                "scoreInfoNum": 3.0,
                "detailChampionId": "50",
                "nickNameStr": "三慕斯#84430",
                "wasSvp": "0",
                "win": "Fail",
                "zhuangbei2": 3116,
                "dengji": "11",
                "zhuangbei1": 3871,
                "zhuangbei4": 1052,
                "zhuangbei3": 3020,
                "biaoxianInfo": [],
                "zhuangbei6": 2508,
                "zhuangbei5": 1028,
                "wasMvp": "0",
                "zhuangbei7": 3364,
                "nickName": "三慕斯#84430",
                "detailSperk4": 8299,
                "detailSperk5": 8429,
                "detailSperk6": 8451,
                "playerSubteam": "0",
                "detailSperk1": 8010,
                "tierInfoId": 0,
                "detailSperk2": 8009,
                "detailSperk3": 9105,
                "detailRune2": 4,
                "detailRune1": 14,
                "qszhl": "1.287",
                "duanweiInfo": "",
                "totalDamageDealt": 13.0,
                "teamId": "200",
                "translateAreaId": 1,
                "position": "UTILITY",
                "openIdNow": "1nDJCnFiaWvqerKbXB4FwchTmzmpc+193mTW89J2kaQ=",
                "guimo": 5
            },
            {
                "scoreInfo": "3/7/7",
                "skinIndexName": "神拳 李青<br>（传说）",
                "echartsMap": {
                    "totalDamageDealtPrv": 14439,
                    "totalDamageTakenPrv": 25714,
                    "killAssisScorePrv": 47,
                    "goldEarned": 9441,
                    "totalDamageTakenInfo": "承伤\n29242\n(25714)",
                    "goldEarnedMax": 11107,
                    "killAssisMax": 100,
                    "scorePrv": 3.9,
                    "score": 4.9,
                    "killAssisScore": 71,
                    "totalDamageDealtMax": 16105,
                    "totalDamageTakenMax": 31908,
                    "totalDamageDealtInfo": "伤害\n12684\n(14439)",
                    "killAssisInfo": "参团\n71%\n(47%)",
                    "gameScoreMax": 4.9,
                    "totalDamageDealt": 12684,
                    "totalDamageTaken": 29242,
                    "goldEarnedPrv": 9249,
                    "goldEarnedInfo": "金币\n9441\n(9249)",
                    "gameScoreInfo": "评分\n4.9\n(3.9)"
                },
                "goldEarned": 9.5,
                "playerSubteamPlacement": "0",
                "skinUrlInfo": "https://wegame.gtimg.com/g.26-r.c2d3c/helper/lol/assis/images/resources/skins/original/64-011.jpg",
                "scoreInfoNum": 4.9,
                "detailChampionId": "64",
                "nickNameStr": "大人头养爹拿SVP#72849",
                "wasSvp": "1",
                "win": "Fail",
                "zhuangbei2": 6610,
                "dengji": "13",
                "zhuangbei1": 6692,
                "zhuangbei4": 2055,
                "zhuangbei3": 3044,
                "biaoxianInfo": [],
                "zhuangbei6": 3067,
                "zhuangbei5": 2422,
                "wasMvp": "0",
                "zhuangbei7": 3340,
                "nickName": "大人头养爹拿SVP#72849",
                "detailSperk4": 8014,
                "detailSperk5": 8304,
                "detailSperk6": 8347,
                "playerSubteam": "0",
                "detailSperk1": 8010,
                "tierInfoId": 0,
                "detailSperk2": 9111,
                "detailSperk3": 9104,
                "detailRune2": 11,
                "detailRune1": 4,
                "qszhl": "0.861",
                "duanweiInfo": "",
                "totalDamageDealt": 12.7,
                "teamId": "200",
                "translateAreaId": 1,
                "position": "JUNGLE",
                "openIdNow": "Df7Jd7YssYb997psolgwgpuP7OcdSDU13mTW89J2kaQ=",
                "guimo": 5
            },
            {
                "scoreInfo": "1/3/23",
                "skinIndexName": "原皮",
                "echartsMap": {
                    "totalDamageDealtPrv": 21365,
                    "totalDamageTakenPrv": 19078,
                    "killAssisScorePrv": 47,
                    "goldEarned": 8609,
                    "totalDamageTakenInfo": "承伤\n11633\n(19078)",
                    "goldEarnedMax": 13501,
                    "killAssisMax": 100,
                    "scorePrv": 8.3,
                    "score": 5.6,
                    "killAssisScore": 62,
                    "totalDamageDealtMax": 23031,
                    "totalDamageTakenMax": 21744,
                    "totalDamageDealtInfo": "伤害\n4929\n(21365)",
                    "killAssisInfo": "参团\n62%\n(47%)",
                    "gameScoreMax": 8.3,
                    "totalDamageDealt": 4929,
                    "totalDamageTaken": 11633,
                    "goldEarnedPrv": 11835,
                    "goldEarnedInfo": "金币\n8609\n(11835)",
                    "gameScoreInfo": "评分\n5.6\n(8.3)"
                },
                "goldEarned": 8.7,
                "playerSubteamPlacement": "0",
                "skinUrlInfo": "https://wegame.gtimg.com/g.26-r.c2d3c/helper/lol/assis/images/resources/skins/original/902-000.jpg",
                "scoreInfoNum": 5.6,
                "detailChampionId": "902",
                "nickNameStr": "青山不解风情#57865",
                "wasSvp": "0",
                "win": "Win",
                "zhuangbei2": 6617,
                "dengji": "13",
                "zhuangbei1": 3869,
                "zhuangbei4": 6620,
                "zhuangbei3": 3158,
                "biaoxianInfo": [
                    "attack",
                    "hurt"
                ],
                "zhuangbei6": 1052,
                "zhuangbei5": 1052,
                "wasMvp": "0",
                "zhuangbei7": 3364,
                "nickName": "青山不解风情#57865",
                "detailSperk4": 8237,
                "detailSperk5": 8473,
                "detailSperk6": 8453,
                "playerSubteam": "0",
                "detailSperk1": 8214,
                "tierInfoId": 0,
                "detailSperk2": 8226,
                "detailSperk3": 8210,
                "detailRune2": 3,
                "detailRune1": 4,
                "qszhl": "0.318",
                "duanweiInfo": "",
                "totalDamageDealt": 5.0,
                "teamId": "100",
                "translateAreaId": 1,
                "position": "UTILITY",
                "openIdNow": "qR7BP+lLToQaMVxcfiKmOmuK0ahp6QzH3mTW89J2kaQ=",
                "guimo": 5
            },
            {
                "scoreInfo": "2/8/0",
                "skinIndexName": "原皮",
                "echartsMap": {
                    "totalDamageDealtPrv": 14439,
                    "totalDamageTakenPrv": 25714,
                    "killAssisScorePrv": 47,
                    "goldEarned": 10483,
                    "totalDamageTakenInfo": "承伤\n29059\n(25714)",
                    "goldEarnedMax": 12149,
                    "killAssisMax": 100,
                    "scorePrv": 3.9,
                    "score": 3.6,
                    "killAssisScore": 14,
                    "totalDamageDealtMax": 16105,
                    "totalDamageTakenMax": 31725,
                    "totalDamageDealtInfo": "伤害\n14204\n(14439)",
                    "killAssisInfo": "参团\n14%\n(47%)",
                    "gameScoreMax": 3.9,
                    "totalDamageDealt": 14204,
                    "totalDamageTaken": 29059,
                    "goldEarnedPrv": 9249,
                    "goldEarnedInfo": "金币\n10483\n(9249)",
                    "gameScoreInfo": "评分\n3.6\n(3.9)"
                },
                "goldEarned": 10.5,
                "playerSubteamPlacement": "0",
                "skinUrlInfo": "https://wegame.gtimg.com/g.26-r.c2d3c/helper/lol/assis/images/resources/skins/original/114-000.jpg",
                "scoreInfoNum": 3.6,
                "detailChampionId": "114",
                "nickNameStr": "其實我也戀長安#59786",
                "wasSvp": "0",
                "win": "Fail",
                "zhuangbei2": 3074,
                "dengji": "15",
                "zhuangbei1": 1001,
                "zhuangbei4": 1037,
                "zhuangbei3": 2021,
                "biaoxianInfo": [
                    "pull"
                ],
                "zhuangbei6": 3078,
                "zhuangbei5": 3066,
                "wasMvp": "0",
                "zhuangbei7": 3340,
                "nickName": "其實我也戀長安#59786",
                "detailSperk4": 8299,
                "detailSperk5": 8446,
                "detailSperk6": 8444,
                "playerSubteam": "0",
                "detailSperk1": 8010,
                "tierInfoId": 0,
                "detailSperk2": 9111,
                "detailSperk3": 9104,
                "detailRune2": 4,
                "detailRune1": 12,
                "qszhl": "0.869",
                "duanweiInfo": "",
                "totalDamageDealt": 14.3,
                "teamId": "200",
                "translateAreaId": 1,
                "position": "TOP",
                "openIdNow": "CTcN67r1p7aBrmBocIoYf7cwaKP2pQt63mTW89J2kaQ=",
                "guimo": 5
            },
            {
                "scoreInfo": "4/5/8",
                "skinIndexName": "古神 魔腾 恸哭之刃<br>（炫彩）",
                "echartsMap": {
                    "totalDamageDealtPrv": 21365,
                    "totalDamageTakenPrv": 19078,
                    "killAssisScorePrv": 47,
                    "goldEarned": 9528,
                    "totalDamageTakenInfo": "承伤\n23779\n(19078)",
                    "goldEarnedMax": 13501,
                    "killAssisMax": 100,
                    "scorePrv": 8.3,
                    "score": 3.9,
                    "killAssisScore": 31,
                    "totalDamageDealtMax": 23031,
                    "totalDamageTakenMax": 26445,
                    "totalDamageDealtInfo": "伤害\n17844\n(21365)",
                    "killAssisInfo": "参团\n31%\n(47%)",
                    "gameScoreMax": 8.3,
                    "totalDamageDealt": 17844,
                    "totalDamageTaken": 23779,
                    "goldEarnedPrv": 11835,
                    "goldEarnedInfo": "金币\n9528\n(11835)",
                    "gameScoreInfo": "评分\n3.9\n(8.3)"
                },
                "goldEarned": 9.6,
                "playerSubteamPlacement": "0",
                "skinUrlInfo": "https://wegame.gtimg.com/g.26-r.c2d3c/helper/lol/assis/images/resources/skins/original/56-007.jpg",
                "scoreInfoNum": 3.9,
                "detailChampionId": "56",
                "nickNameStr": "泰隆0u0#66922",
                "wasSvp": "0",
                "win": "Win",
                "zhuangbei2": 1055,
                "dengji": "15",
                "zhuangbei1": 6631,
                "zhuangbei4": 3073,
                "zhuangbei3": 3174,
                "biaoxianInfo": [],
                "zhuangbei6": 0,
                "zhuangbei5": 1037,
                "wasMvp": "0",
                "zhuangbei7": 3363,
                "nickName": "泰隆0u0#66922",
                "detailSperk4": 8299,
                "detailSperk5": 8106,
                "detailSperk6": 8139,
                "playerSubteam": "0",
                "detailSperk1": 8010,
                "tierInfoId": 0,
                "detailSperk2": 9111,
                "detailSperk3": 9104,
                "detailRune2": 14,
                "detailRune1": 4,
                "qszhl": "1.038",
                "duanweiInfo": "",
                "totalDamageDealt": 17.9,
                "teamId": "100",
                "translateAreaId": 1,
                "position": "MIDDLE",
                "openIdNow": "MFP+PU3GinuHRZr3H2p4QlxRtONDgTSg3mTW89J2kaQ=",
                "guimo": 5
            },
            {
                "scoreInfo": "11/3/7",
                "skinIndexName": "虚空海灵 菲兹<br>（史诗）",
                "echartsMap": {
                    "totalDamageDealtPrv": 21365,
                    "totalDamageTakenPrv": 19078,
                    "killAssisScorePrv": 47,
                    "goldEarned": 13165,
                    "totalDamageTakenInfo": "承伤\n23719\n(19078)",
                    "goldEarnedMax": 14831,
                    "killAssisMax": 100,
                    "scorePrv": 8.3,
                    "score": 9.1,
                    "killAssisScore": 46,
                    "totalDamageDealtMax": 24890,
                    "totalDamageTakenMax": 26385,
                    "totalDamageDealtInfo": "伤害\n23224\n(21365)",
                    "killAssisInfo": "参团\n46%\n(47%)",
                    "gameScoreMax": 9.1,
                    "totalDamageDealt": 23224,
                    "totalDamageTaken": 23719,
                    "goldEarnedPrv": 11835,
                    "goldEarnedInfo": "金币\n13165\n(11835)",
                    "gameScoreInfo": "评分\n9.1\n(8.3)"
                },
                "goldEarned": 13.2,
                "playerSubteamPlacement": "0",
                "skinUrlInfo": "https://wegame.gtimg.com/g.26-r.c2d3c/helper/lol/assis/images/resources/skins/original/105-004.jpg",
                "scoreInfoNum": 9.1,
                "detailChampionId": "105",
                "nickNameStr": "晨星候暮#68918",
                "wasSvp": "0",
                "win": "Win",
                "zhuangbei2": 2055,
                "dengji": "15",
                "zhuangbei1": 3158,
                "zhuangbei4": 3041,
                "zhuangbei3": 3157,
                "biaoxianInfo": [],
                "zhuangbei6": 2510,
                "zhuangbei5": 4645,
                "wasMvp": "0",
                "zhuangbei7": 3364,
                "nickName": "晨星候暮#68918",
                "detailSperk4": 8014,
                "detailSperk5": 8313,
                "detailSperk6": 8347,
                "playerSubteam": "0",
                "detailSperk1": 8005,
                "tierInfoId": 0,
                "detailSperk2": 9111,
                "detailSperk3": 9105,
                "detailRune2": 4,
                "detailRune1": 11,
                "qszhl": "0.978",
                "duanweiInfo": "",
                "totalDamageDealt": 23.3,
                "teamId": "100",
                "translateAreaId": 1,
                "position": "JUNGLE",
                "openIdNow": "d8JFKHbNe1TLA7Q+Z98kMGC3SuHSvb+T3mTW89J2kaQ=",
                "guimo": 5
            }
        ],
        "teamDetails": [
            {
                "banInfoList": [
                    {
                        "championId": 421,
                        "pickTurn": 1,
                        "teamId": "100"
                    },
                    {
                        "championId": 104,
                        "pickTurn": 3,
                        "teamId": "100"
                    },
                    {
                        "championId": 131,
                        "pickTurn": 5,
                        "teamId": "100"
                    },
                    {
                        "championId": 498,
                        "pickTurn": 8,
                        "teamId": "100"
                    },
                    {
                        "championId": 21,
                        "pickTurn": 10,
                        "teamId": "100"
                    }
                ],
                "totalBaseKilled": 1,
                "totalKills": 39,
                "isSurrender": 1,
                "totalTurretsKilled": 7,
                "totalDampenKilled": 1,
                "totalAssists": 53,
                "totalDeaths": 14,
                "totalDragonKills": 4,
                "teamId": "100",
                "totalGoldEarned": 59173,
                "totalBaronKills": 1,
                "win": "Win"
            },
            {
                "banInfoList": [
                    {
                        "championId": 799,
                        "pickTurn": 2,
                        "teamId": "200"
                    },
                    {
                        "championId": 127,
                        "pickTurn": 4,
                        "teamId": "200"
                    },
                    {
                        "championId": 875,
                        "pickTurn": 6,
                        "teamId": "200"
                    },
                    {
                        "championId": 523,
                        "pickTurn": 7,
                        "teamId": "200"
                    },
                    {
                        "championId": 236,
                        "pickTurn": 9,
                        "teamId": "200"
                    }
                ],
                "totalBaseKilled": 0,
                "totalKills": 14,
                "isSurrender": 1,
                "totalTurretsKilled": 3,
                "totalDampenKilled": 0,
                "totalAssists": 19,
                "totalDeaths": 39,
                "totalDragonKills": 0,
                "teamId": "200",
                "totalGoldEarned": 46245,
                "totalBaronKills": 0,
                "win": "Fail"
            }
        ]
    }
}